gpumeter/__init__.py
gpumeter/meter.py
gpumeter-1.0.3.dist-info/METADATA
gpumeter-1.0.3.dist-info/WHEEL
gpumeter-1.0.3.dist-info/top_level.txt
gpumeter-1.0.3.dist-info/RECORD
